grafter/__init__.py
grafter-0.1.dist-info/LICENSE
grafter-0.1.dist-info/METADATA
grafter-0.1.dist-info/WHEEL
grafter-0.1.dist-info/entry_points.txt
grafter-0.1.dist-info/top_level.txt
grafter-0.1.dist-info/RECORD
