Metadata-Version: 2.1
Name: grafter
Version: 0.1
Summary: create correspondance tables with semantic meaning
Home-page: https://github.com/BONSAMURAIS/grafter
Author: BONSAI team
Author-email: info@bonsai.uno
License: BSD 3-Clause License
Requires-Dist: appdirs
Requires-Dist: docopt
